watson/__init__.py
watson/serialize/__init__.py
watson/serialize/decorators.py
watson/serialize/errors.py
watson/serialize/serializers.py
watson_serialize-1.1.5.dist-info/AUTHORS
watson_serialize-1.1.5.dist-info/LICENSE
watson_serialize-1.1.5.dist-info/METADATA
watson_serialize-1.1.5.dist-info/WHEEL
watson_serialize-1.1.5.dist-info/top_level.txt
watson_serialize-1.1.5.dist-info/RECORD
