Metadata-Version: 2.1
Name: watson-serialize
Version: 1.1.5
Summary: Serialize objects and classes for use in REST APIs.
Home-page: http://github.com/watsonpy/watson-serialize
Author: Simon Coulton
Author-email: simon@bespohk.com
License: Copyright (c) Bespohk and individual contributors.
Requires-Dist: watson-db (>=2.7.0)
Provides-Extra: test
Requires-Dist: pytest ; extra == 'test'
Requires-Dist: pytest-cov ; extra == 'test'
Requires-Dist: coverage ; extra == 'test'
Requires-Dist: coveralls ; extra == 'test'
